{"v":"4.8.0","meta":{"g":"LottieFiles AE 1.0.0","a":"Bas Milius","k":"Meteocons, Weather icons, Icon set","d":"UV Index 8 - Meteocons.com","tc":""},"fr":60,"ip":0,"op":360,"w":512,"h":512,"nm":"uv-index-8","ddd":0,"assets":[],"layers":[{"ddd":0,"ind":1,"ty":4,"nm":"uv","sr":1,"ks":{"o":{"a":0,"k":100,"ix":11},"r":{"a":0,"k":0,"ix":10},"p":{"a":0,"k":[352,352,0],"ix":2},"a":{"a":0,"k":[352,352,0],"ix":1},"s":{"a":0,"k":[100,100,100],"ix":6}},"ao":0,"shapes":[{"ind":0,"ty":"sh","ix":1,"ks":{"a":0,"k":{"i":[[-3.406,0],[-1.896,1.479],[0,2.635],[1.863,1.382],[3.404,0],[0,-5.332],[-1.896,-1.477]],"o":[[3.34,0],[1.894,-1.477],[0,-2.569],[-1.863,-1.381],[-7.197,0],[0,2.635],[1.894,1.479]],"v":[[352.048,344.722],[359.904,342.506],[362.747,336.337],[359.951,330.409],[352.048,328.338],[341.253,336.337],[344.096,342.506]],"c":true},"ix":2},"nm":"Path 1","mn":"ADBE Vector Shape - Group","hd":false},{"ind":1,"ty":"sh","ix":2,"ks":{"a":0,"k":{"i":[[-3.855,0],[-2.185,1.702],[0,3.022],[2.151,1.704],[3.855,0],[2.183,-1.7],[0,-3.02],[-2.216,-1.702]],"o":[[3.79,0],[2.185,-1.702],[0,-3.02],[-2.155,-1.7],[-3.92,0],[-2.186,1.704],[0,3.022],[2.218,1.702]],"v":[[352.048,375.083],[361.012,372.53],[364.288,365.445],[361.061,358.36],[352.048,355.807],[342.892,358.36],[339.614,365.445],[342.939,372.53]],"c":true},"ix":2},"nm":"Path 2","mn":"ADBE Vector Shape - Group","hd":false},{"ind":2,"ty":"sh","ix":3,"ks":{"a":0,"k":{"i":[[5.267,-3.918],[9.06,0],[5.269,3.922],[0,6.812],[-2.347,2.859],[-4.242,1.03],[0,0],[1.832,2.602],[0,3.406],[-4.595,3.31],[-8.226,0],[-4.626,-3.31],[0,-5.848],[1.832,-2.604],[3.147,-1.028],[0,0],[-2.314,-2.826],[0,-4.242]],"o":[[-5.271,3.922],[-8.997,0],[-5.269,-3.918],[0,-4.242],[2.343,-2.859],[0,0],[-3.149,-1.092],[-1.83,-2.602],[0,-5.848],[4.593,-3.31],[8.289,0],[4.628,3.31],[0,3.469],[-1.83,2.602],[0,0],[4.242,1.094],[2.312,2.83],[0,6.812]],"v":[[373.446,382.119],[351.952,388],[330.554,382.119],[322.652,366.024],[326.169,355.374],[336.049,349.542],[336.049,349.254],[328.578,343.71],[325.832,334.7],[332.723,320.965],[351.952,316],[371.324,320.965],[378.264,334.7],[375.517,343.808],[368.047,349.254],[368.047,349.542],[377.88,355.421],[381.348,366.024]],"c":true},"ix":2},"nm":"Path 3","mn":"ADBE Vector Shape - Group","hd":false},{"ty":"fl","c":{"a":0,"k":[1,1,1,1],"ix":4},"o":{"a":0,"k":100,"ix":5},"r":1,"bm":0,"nm":"Fill 1","mn":"ADBE Vector Graphic - Fill","hd":false},{"ind":4,"ty":"sh","ix":5,"ks":{"a":0,"k":{"i":[[26.4,0],[0,0],[0,26.4],[0,0],[-26.4,0],[0,0],[0,-26.4],[0,0]],"o":[[0,0],[-26.4,0],[0,0],[0,-26.4],[0,0],[26.4,0],[0,0],[0,26.4]],"v":[[376,424],[328,424],[280,376],[280,328],[328,280],[376,280],[424,328],[424,376]],"c":true},"ix":2},"nm":"Path 4","mn":"ADBE Vector Shape - Group","hd":false},{"ty":"fl","c":{"a":0,"k":[1,0.235294118524,0,1],"ix":4},"o":{"a":0,"k":100,"ix":5},"r":1,"bm":0,"nm":"Fill 2","mn":"ADBE Vector Graphic - Fill","hd":false}],"ip":0,"op":360,"st":0,"bm":0},{"ddd":0,"ind":2,"ty":4,"nm":"sun","sr":1,"ks":{"o":{"a":0,"k":100,"ix":11},"r":{"a":0,"k":0,"ix":10},"p":{"a":0,"k":[256,256,0],"ix":2},"a":{"a":0,"k":[0,0,0],"ix":1},"s":{"a":0,"k":[100,100,100],"ix":6}},"ao":0,"hasMask":true,"masksProperties":[{"inv":false,"mode":"a","pt":{"a":0,"k":{"i":[[0,0],[0,0],[0,0],[0,0],[0,-39.761],[0,0],[0,0]],"o":[[0,0],[0,0],[0,0],[-39.761,0],[0,0],[0,0],[0,0]],"v":[[-191.5,-191.5],[192.5,-191.5],[192.5,0.5],[72.494,0.5],[0.5,72.494],[0.5,192.5],[-191.5,192.5]],"c":true},"ix":1},"o":{"a":0,"k":100,"ix":3},"x":{"a":0,"k":0,"ix":4},"nm":"Mask 1"}],"shapes":[{"ty":"gr","it":[{"ind":0,"ty":"sh","ix":1,"ks":{"a":0,"k":{"i":[[0,-46.392],[46.392,0],[0,46.392],[-46.392,0]],"o":[[0,46.392],[-46.392,0],[0,-46.392],[46.392,0]],"v":[[84,0],[0,84],[-84,0],[0,-84]],"c":true},"ix":2},"nm":"Path 1","mn":"ADBE Vector Shape - Group","hd":false},{"ty":"st","c":{"a":0,"k":[0.984313726425,0.749019622803,0.141176477075,1],"ix":3},"o":{"a":0,"k":100,"ix":4},"w":{"a":0,"k":15,"ix":5},"lc":1,"lj":1,"ml":10,"bm":0,"nm":"Stroke 1","mn":"ADBE Vector Graphic - Stroke","hd":false},{"ty":"tr","p":{"a":0,"k":[0,0],"ix":2},"a":{"a":0,"k":[0,0],"ix":1},"s":{"a":0,"k":[100,100],"ix":3},"r":{"a":0,"k":0,"ix":6},"o":{"a":0,"k":100,"ix":7},"sk":{"a":0,"k":0,"ix":4},"sa":{"a":0,"k":0,"ix":5},"nm":"Transform"}],"nm":"core","np":2,"cix":2,"bm":0,"ix":1,"mn":"ADBE Vector Group","hd":false},{"ty":"gr","it":[{"ind":0,"ty":"sh","ix":1,"ks":{"a":0,"k":{"i":[[0,0],[0,0]],"o":[[0,0],[0,0]],"v":[[180,0],[130.345,0]],"c":false},"ix":2},"nm":"Path 1","mn":"ADBE Vector Shape - Group","hd":false},{"ind":1,"ty":"sh","ix":2,"ks":{"a":0,"k":{"i":[[0,0],[0,0]],"o":[[0,0],[0,0]],"v":[[-130.345,0],[-180,0]],"c":false},"ix":2},"nm":"Path 2","mn":"ADBE Vector Shape - Group","hd":false},{"ind":2,"ty":"sh","ix":3,"ks":{"a":0,"k":{"i":[[0,0],[0,0]],"o":[[0,0],[0,0]],"v":[[127.279,127.279],[92.168,92.168]],"c":false},"ix":2},"nm":"Path 3","mn":"ADBE Vector Shape - Group","hd":false},{"ind":3,"ty":"sh","ix":4,"ks":{"a":0,"k":{"i":[[0,0],[0,0]],"o":[[0,0],[0,0]],"v":[[-92.168,-92.168],[-127.279,-127.279]],"c":false},"ix":2},"nm":"Path 4","mn":"ADBE Vector Shape - Group","hd":false},{"ind":4,"ty":"sh","ix":5,"ks":{"a":0,"k":{"i":[[0,0],[0,0]],"o":[[0,0],[0,0]],"v":[[-127.279,127.279],[-92.168,92.168]],"c":false},"ix":2},"nm":"Path 5","mn":"ADBE Vector Shape - Group","hd":false},{"ind":5,"ty":"sh","ix":6,"ks":{"a":0,"k":{"i":[[0,0],[0,0]],"o":[[0,0],[0,0]],"v":[[92.168,-92.168],[127.279,-127.279]],"c":false},"ix":2},"nm":"Path 6","mn":"ADBE Vector Shape - Group","hd":false},{"ind":6,"ty":"sh","ix":7,"ks":{"a":0,"k":{"i":[[0,0],[0,0]],"o":[[0,0],[0,0]],"v":[[0,180],[0,130.345]],"c":false},"ix":2},"nm":"Path 7","mn":"ADBE Vector Shape - Group","hd":false},{"ind":7,"ty":"sh","ix":8,"ks":{"a":0,"k":{"i":[[0,0],[0,0]],"o":[[0,0],[0,0]],"v":[[0,-130.345],[0,-180]],"c":false},"ix":2},"nm":"Path 8","mn":"ADBE Vector Shape - Group","hd":false},{"ty":"st","c":{"a":0,"k":[0.984313726425,0.749019622803,0.141176477075,1],"ix":3},"o":{"a":0,"k":100,"ix":4},"w":{"a":0,"k":15,"ix":5},"lc":2,"lj":1,"ml":10,"bm":0,"nm":"Stroke 1","mn":"ADBE Vector Graphic - Stroke","hd":false},{"ty":"tr","p":{"a":0,"k":[0,0],"ix":2},"a":{"a":0,"k":[0,0],"ix":1},"s":{"a":0,"k":[100,100],"ix":3},"r":{"a":1,"k":[{"i":{"x":[0.833],"y":[0.833]},"o":{"x":[0.167],"y":[0.167]},"t":0,"s":[0]},{"t":359,"s":[45]}],"ix":6},"o":{"a":0,"k":100,"ix":7},"sk":{"a":0,"k":0,"ix":4},"sa":{"a":0,"k":0,"ix":5},"nm":"Transform"}],"nm":"rays","np":9,"cix":2,"bm":0,"ix":2,"mn":"ADBE Vector Group","hd":false},{"ty":"gr","it":[{"ind":0,"ty":"sh","ix":1,"ks":{"a":0,"k":{"i":[[0,0],[0,0],[-40.859,0],[0,0]],"o":[[0,0],[0,-40.859],[0,0],[0,0]],"v":[[-2,82],[-2,71.982],[71.982,-2],[82,-2]],"c":false},"ix":2},"nm":"Path 1","mn":"ADBE Vector Shape - Group","hd":false},{"ty":"st","c":{"a":0,"k":[0.984313726425,0.749019622803,0.141176477075,1],"ix":3},"o":{"a":0,"k":100,"ix":4},"w":{"a":0,"k":15,"ix":5},"lc":1,"lj":1,"ml":10,"bm":0,"nm":"Stroke 1","mn":"ADBE Vector Graphic - Stroke","hd":false},{"ty":"tr","p":{"a":0,"k":[0,0],"ix":2},"a":{"a":0,"k":[0,0],"ix":1},"s":{"a":0,"k":[100,100],"ix":3},"r":{"a":0,"k":0,"ix":6},"o":{"a":0,"k":100,"ix":7},"sk":{"a":0,"k":0,"ix":4},"sa":{"a":0,"k":0,"ix":5},"nm":"Transform"}],"nm":"fix","np":2,"cix":2,"bm":0,"ix":3,"mn":"ADBE Vector Group","hd":false}],"ip":0,"op":360,"st":0,"bm":0}],"markers":[]}